{
  "name" : "Room",
  "preName" : "",
  "comment" : "客房表",
  "templateGroupName" : "Default",
  "fullColumn" : [ {
    "name" : "roomid",
    "comment" : null,
    "type" : null,
    "shortType" : null,
    "custom" : false,
    "ext" : { }
  }, {
    "name" : "roomNum",
    "comment" : null,
    "type" : null,
    "shortType" : null,
    "custom" : false,
    "ext" : { }
  }, {
    "name" : "rtypeid",
    "comment" : null,
    "type" : null,
    "shortType" : null,
    "custom" : false,
    "ext" : { }
  }, {
    "name" : "isres",
    "comment" : null,
    "type" : null,
    "shortType" : null,
    "custom" : false,
    "ext" : { }
  }, {
    "name" : "state",
    "comment" : null,
    "type" : null,
    "shortType" : null,
    "custom" : false,
    "ext" : { }
  }, {
    "name" : "remark",
    "comment" : null,
    "type" : null,
    "shortType" : null,
    "custom" : false,
    "ext" : { }
  } ],
  "pkColumn" : null,
  "otherColumn" : null,
  "savePackageName" : "com.hotel",
  "savePath" : "./src/main/java/com/hotel",
  "saveModelName" : "hotelCoding"
}